{"learner":{"attributes":{"best_iteration":"99","best_ntree_limit":"100","scikit_learn":"{\"n_estimators\": 100, \"objective\": \"reg:squarederror\", \"max_depth\": null, \"max_leaves\": null, \"max_bin\": null, \"grow_policy\": null, \"learning_rate\": null, \"verbosity\": null, \"booster\": null, \"tree_method\": null, \"gamma\": null, \"min_child_weight\": null, \"max_delta_step\": null, \"subsample\": null, \"sampling_method\": null, \"colsample_bytree\": null, \"colsample_bylevel\": null, \"colsample_bynode\": null, \"reg_alpha\": null, \"reg_lambda\": null, \"scale_pos_weight\": null, \"base_score\": null, \"missing\": NaN, \"num_parallel_tree\": null, \"random_state\": null, \"n_jobs\": null, \"monotone_constraints\": null, \"interaction_constraints\": null, \"importance_type\": null, \"gpu_id\": null, \"validate_parameters\": null, \"predictor\": null, \"enable_categorical\": false, \"feature_types\": null, \"max_cat_to_onehot\": null, \"max_cat_threshold\": null, \"eval_metric\": null, \"early_stopping_rounds\": null, \"callbacks\": null, \"_estimator_type\": \"regressor\"}"},"feature_names":[],"feature_types":[],"gradient_booster":{"model":{"gbtree_model_param":{"num_parallel_tree":"1","num_trees":"100","size_leaf_vector":"0"},"tree_info":[0,0,0,0,0,0,0,0,0,0,0,0,0,0,0,0,0,0,0,0,0,0,0,0,0,0,0,0,0,0,0,0,0,0,0,0,0,0,0,0,0,0,0,0,0,0,0,0,0,0,0,0,0,0,0,0,0,0,0,0,0,0,0,0,0,0,0,0,0,0,0,0,0,0,0,0,0,0,0,0,0,0,0,0,0,0,0,0,0,0,0,0,0,0,0,0,0,0,0,0],"trees":[{"base_weights":[1.5451563E1],"categories":[],"categories_nodes":[],"categories_segments":[],"categories_sizes":[],"default_left":[0],"id":0,"left_children":[-1],"loss_changes":[0E0],"parents":[2147483647],"right_children":[-1],"split_conditions":[4.635469E0],"split_indices":[0],"split_type":[0],"sum_hessian":[3.19E2],"tree_param":{"num_deleted":"0","num_feature":"4","num_nodes":"1","size_leaf_vector":"0"}},{"base_weights":[1.0830579E1],"categories":[],"categories_nodes":[],"categories_segments":[],"categories_sizes":[],"default_left":[0],"id":1,"left_children":[-1],"loss_changes":[0E0],"parents":[2147483647],"right_children":[-1],"split_conditions":[3.2491739E0],"split_indices":[0],"split_type":[0],"sum_hessian":[3.19E2],"tree_param":{"num_deleted":"0","num_feature":"4","num_nodes":"1","size_leaf_vector":"0"}},{"base_weights":[7.5915594E0],"categories":[],"categories_nodes":[],"categories_segments":[],"categories_sizes":[],"default_left":[0],"id":2,"left_children":[-1],"loss_changes":[0E0],"parents":[2147483647],"right_children":[-1],"split_conditions":[2.277468E0],"split_indices":[0],"split_type":[0],"sum_hessian":[3.19E2],"tree_param":{"num_deleted":"0","num_feature":"4","num_nodes":"1","size_leaf_vector":"0"}},{"base_weights":[5.321209E0],"categories":[],"categories_nodes":[],"categories_segments":[],"categories_sizes":[],"default_left":[0],"id":3,"left_children":[-1],"loss_changes":[0E0],"parents":[2147483647],"right_children":[-1],"split_conditions":[1.5963627E0],"split_indices":[0],"split_type":[0],"sum_hessian":[3.19E2],"tree_param":{"num_deleted":"0","num_feature":"4","num_nodes":"1","size_leaf_vector":"0"}},{"base_weights":[3.7298343E0],"categories":[],"categories_nodes":[],"categories_segments":[],"categories_sizes":[],"default_left":[0],"id":4,"left_children":[-1],"loss_changes":[0E0],"parents":[2147483647],"right_children":[-1],"split_conditions":[1.1189504E0],"split_indices":[0],"split_type":[0],"sum_hessian":[3.19E2],"tree_param":{"num_deleted":"0","num_feature":"4","num_nodes":"1","size_leaf_vector":"0"}},{"base_weights":[2.6143801E0],"categories":[],"categories_nodes":[],"categories_segments":[],"categories_sizes":[],"default_left":[0],"id":5,"left_children":[-1],"loss_changes":[0E0],"parents":[2147483647],"right_children":[-1],"split_conditions":[7.843141E-1],"split_indices":[0],"split_type":[0],"sum_hessian":[3.19E2],"tree_param":{"num_deleted":"0","num_feature":"4","num_nodes":"1","size_leaf_vector":"0"}},{"base_weights":[1.832517E0],"categories":[],"categories_nodes":[],"categories_segments":[],"categories_sizes":[],"default_left":[0],"id":6,"left_children":[-1],"loss_changes":[0E0],"parents":[2147483647],"right_children":[-1],"split_conditions":[5.4975516E-1],"split_indices":[0],"split_type":[0],"sum_hessian":[3.19E2],"tree_param":{"num_deleted":"0","num_feature":"4","num_nodes":"1","size_leaf_vector":"0"}},{"base_weights":[1.28448E0],"categories":[],"categories_nodes":[],"categories_segments":[],"categories_sizes":[],"default_left":[0],"id":7,"left_children":[-1],"loss_changes":[0E0],"parents":[2147483647],"right_children":[-1],"split_conditions":[3.85344E-1],"split_indices":[0],"split_type":[0],"sum_hessian":[3.19E2],"tree_param":{"num_deleted":"0","num_feature":"4","num_nodes":"1","size_leaf_vector":"0"}},{"base_weights":[9.0034056E-1],"categories":[],"categories_nodes":[],"categories_segments":[],"categories_sizes":[],"default_left":[0],"id":8,"left_children":[-1],"loss_changes":[0E0],"parents":[2147483647],"right_children":[-1],"split_conditions":[2.7010217E-1],"split_indices":[0],"split_type":[0],"sum_hessian":[3.19E2],"tree_param":{"num_deleted":"0","num_feature":"4","num_nodes":"1","size_leaf_vector":"0"}},{"base_weights":[6.310821E-1],"categories":[],"categories_nodes":[],"categories_segments":[],"categories_sizes":[],"default_left":[0],"id":9,"left_children":[-1],"loss_changes":[0E0],"parents":[2147483647],"right_children":[-1],"split_conditions":[1.8932465E-1],"split_indices":[0],"split_type":[0],"sum_hessian":[3.19E2],"tree_param":{"num_deleted":"0","num_feature":"4","num_nodes":"1","size_leaf_vector":"0"}},{"base_weights":[4.423494E-1],"categories":[],"categories_nodes":[],"categories_segments":[],"categories_sizes":[],"default_left":[0],"id":10,"left_children":[-1],"loss_changes":[0E0],"parents":[2147483647],"right_children":[-1],"split_conditions":[1.3270482E-1],"split_indices":[0],"split_type":[0],"sum_hessian":[3.19E2],"tree_param":{"num_deleted":"0","num_feature":"4","num_nodes":"1","size_leaf_vector":"0"}},{"base_weights":[3.1005937E-1],"categories":[],"categories_nodes":[],"categories_segments":[],"categories_sizes":[],"default_left":[0],"id":11,"left_children":[-1],"loss_changes":[0E0],"parents":[2147483647],"right_children":[-1],"split_conditions":[9.301782E-2],"split_indices":[0],"split_type":[0],"sum_hessian":[3.19E2],"tree_param":{"num_deleted":"0","num_feature":"4","num_nodes":"1","size_leaf_vector":"0"}},{"base_weights":[2.1733247E-1],"categories":[],"categories_nodes":[],"categories_segments":[],"categories_sizes":[],"default_left":[0],"id":12,"left_children":[-1],"loss_changes":[0E0],"parents":[2147483647],"right_children":[-1],"split_conditions":[6.519974E-2],"split_indices":[0],"split_type":[0],"sum_hessian":[3.19E2],"tree_param":{"num_deleted":"0","num_feature":"4","num_nodes":"1","size_leaf_vector":"0"}},{"base_weights":[1.5233637E-1],"categories":[],"categories_nodes":[],"categories_segments":[],"categories_sizes":[],"default_left":[0],"id":13,"left_children":[-1],"loss_changes":[0E0],"parents":[2147483647],"right_children":[-1],"split_conditions":[4.5700915E-2],"split_indices":[0],"split_type":[0],"sum_hessian":[3.19E2],"tree_param":{"num_deleted":"0","num_feature":"4","num_nodes":"1","size_leaf_vector":"0"}},{"base_weights":[1.0677816E-1],"categories":[],"categories_nodes":[],"categories_segments":[],"categories_sizes":[],"default_left":[0],"id":14,"left_children":[-1],"loss_changes":[0E0],"parents":[2147483647],"right_children":[-1],"split_conditions":[3.203345E-2],"split_indices":[0],"split_type":[0],"sum_hessian":[3.19E2],"tree_param":{"num_deleted":"0","num_feature":"4","num_nodes":"1","size_leaf_vector":"0"}},{"base_weights":[7.4844345E-2],"categories":[],"categories_nodes":[],"categories_segments":[],"categories_sizes":[],"default_left":[0],"id":15,"left_children":[-1],"loss_changes":[0E0],"parents":[2147483647],"right_children":[-1],"split_conditions":[2.2453304E-2],"split_indices":[0],"split_type":[0],"sum_hessian":[3.19E2],"tree_param":{"num_deleted":"0","num_feature":"4","num_nodes":"1","size_leaf_vector":"0"}},{"base_weights":[5.24612E-2],"categories":[],"categories_nodes":[],"categories_segments":[],"categories_sizes":[],"default_left":[0],"id":16,"left_children":[-1],"loss_changes":[0E0],"parents":[2147483647],"right_children":[-1],"split_conditions":[1.573836E-2],"split_indices":[0],"split_type":[0],"sum_hessian":[3.19E2],"tree_param":{"num_deleted":"0","num_feature":"4","num_nodes":"1","size_leaf_vector":"0"}},{"base_weights":[3.6771897E-2],"categories":[],"categories_nodes":[],"categories_segments":[],"categories_sizes":[],"default_left":[0],"id":17,"left_children":[-1],"loss_changes":[0E0],"parents":[2147483647],"right_children":[-1],"split_conditions":[1.103157E-2],"split_indices":[0],"split_type":[0],"sum_hessian":[3.19E2],"tree_param":{"num_deleted":"0","num_feature":"4","num_nodes":"1","size_leaf_vector":"0"}},{"base_weights":[2.5775218E-2],"categories":[],"categories_nodes":[],"categories_segments":[],"categories_sizes":[],"default_left":[0],"id":18,"left_children":[-1],"loss_changes":[0E0],"parents":[2147483647],"right_children":[-1],"split_conditions":[7.732566E-3],"split_indices":[0],"split_type":[0],"sum_hessian":[3.19E2],"tree_param":{"num_deleted":"0","num_feature":"4","num_nodes":"1","size_leaf_vector":"0"}},{"base_weights":[1.8066991E-2],"categories":[],"categories_nodes":[],"categories_segments":[],"categories_sizes":[],"default_left":[0],"id":19,"left_children":[-1],"loss_changes":[0E0],"parents":[2147483647],"right_children":[-1],"split_conditions":[5.4200976E-3],"split_indices":[0],"split_type":[0],"sum_hessian":[3.19E2],"tree_param":{"num_deleted":"0","num_feature":"4","num_nodes":"1","size_leaf_vector":"0"}},{"base_weights":[1.2664196E-2],"categories":[],"categories_nodes":[],"categories_segments":[],"categories_sizes":[],"default_left":[0],"id":20,"left_children":[-1],"loss_changes":[0E0],"parents":[2147483647],"right_children":[-1],"split_conditions":[3.799259E-3],"split_indices":[0],"split_type":[0],"sum_hessian":[3.19E2],"tree_param":{"num_deleted":"0","num_feature":"4","num_nodes":"1","size_leaf_vector":"0"}},{"base_weights":[8.876631E-3],"categories":[],"categories_nodes":[],"categories_segments":[],"categories_sizes":[],"default_left":[0],"id":21,"left_children":[-1],"loss_changes":[0E0],"parents":[2147483647],"right_children":[-1],"split_conditions":[2.6629893E-3],"split_indices":[0],"split_type":[0],"sum_hessian":[3.19E2],"tree_param":{"num_deleted":"0","num_feature":"4","num_nodes":"1","size_leaf_vector":"0"}},{"base_weights":[6.222293E-3],"categories":[],"categories_nodes":[],"categories_segments":[],"categories_sizes":[],"default_left":[0],"id":22,"left_children":[-1],"loss_changes":[0E0],"parents":[2147483647],"right_children":[-1],"split_conditions":[1.8666879E-3],"split_indices":[0],"split_type":[0],"sum_hessian":[3.19E2],"tree_param":{"num_deleted":"0","num_feature":"4","num_nodes":"1","size_leaf_vector":"0"}},{"base_weights":[4.3617846E-3],"categories":[],"categories_nodes":[],"categories_segments":[],"categories_sizes":[],"default_left":[0],"id":23,"left_children":[-1],"loss_changes":[0E0],"parents":[2147483647],"right_children":[-1],"split_conditions":[1.3085355E-3],"split_indices":[0],"split_type":[0],"sum_hessian":[3.19E2],"tree_param":{"num_deleted":"0","num_feature":"4","num_nodes":"1","size_leaf_vector":"0"}},{"base_weights":[3.0574321E-3],"categories":[],"categories_nodes":[],"categories_segments":[],"categories_sizes":[],"default_left":[0],"id":24,"left_children":[-1],"loss_changes":[0E0],"parents":[2147483647],"right_children":[-1],"split_conditions":[9.172297E-4],"split_indices":[0],"split_type":[0],"sum_hessian":[3.19E2],"tree_param":{"num_deleted":"0","num_feature":"4","num_nodes":"1","size_leaf_vector":"0"}},{"base_weights":[2.1428645E-3],"categories":[],"categories_nodes":[],"categories_segments":[],"categories_sizes":[],"default_left":[0],"id":25,"left_children":[-1],"loss_changes":[0E0],"parents":[2147483647],"right_children":[-1],"split_conditions":[6.428594E-4],"split_indices":[0],"split_type":[0],"sum_hessian":[3.19E2],"tree_param":{"num_deleted":"0","num_feature":"4","num_nodes":"1","size_leaf_vector":"0"}},{"base_weights":[1.5020967E-3],"categories":[],"categories_nodes":[],"categories_segments":[],"categories_sizes":[],"default_left":[0],"id":26,"left_children":[-1],"loss_changes":[0E0],"parents":[2147483647],"right_children":[-1],"split_conditions":[4.50629E-4],"split_indices":[0],"split_type":[0],"sum_hessian":[3.19E2],"tree_param":{"num_deleted":"0","num_feature":"4","num_nodes":"1","size_leaf_vector":"0"}},{"base_weights":[1.0524184E-3],"categories":[],"categories_nodes":[],"categories_segments":[],"categories_sizes":[],"default_left":[0],"id":27,"left_children":[-1],"loss_changes":[0E0],"parents":[2147483647],"right_children":[-1],"split_conditions":[3.157255E-4],"split_indices":[0],"split_type":[0],"sum_hessian":[3.19E2],"tree_param":{"num_deleted":"0","num_feature":"4","num_nodes":"1","size_leaf_vector":"0"}},{"base_weights":[7.377386E-4],"categories":[],"categories_nodes":[],"categories_segments":[],"categories_sizes":[],"default_left":[0],"id":28,"left_children":[-1],"loss_changes":[0E0],"parents":[2147483647],"right_children":[-1],"split_conditions":[2.2132159E-4],"split_indices":[0],"split_type":[0],"sum_hessian":[3.19E2],"tree_param":{"num_deleted":"0","num_feature":"4","num_nodes":"1","size_leaf_vector":"0"}},{"base_weights":[5.1717757E-4],"categories":[],"categories_nodes":[],"categories_segments":[],"categories_sizes":[],"default_left":[0],"id":29,"left_children":[-1],"loss_changes":[0E0],"parents":[2147483647],"right_children":[-1],"split_conditions":[1.5515328E-4],"split_indices":[0],"split_type":[0],"sum_hessian":[3.19E2],"tree_param":{"num_deleted":"0","num_feature":"4","num_nodes":"1","size_leaf_vector":"0"}},{"base_weights":[3.6221446E-4],"categories":[],"categories_nodes":[],"categories_segments":[],"categories_sizes":[],"default_left":[0],"id":30,"left_children":[-1],"loss_changes":[0E0],"parents":[2147483647],"right_children":[-1],"split_conditions":[1.0866434E-4],"split_indices":[0],"split_type":[0],"sum_hessian":[3.19E2],"tree_param":{"num_deleted":"0","num_feature":"4","num_nodes":"1","size_leaf_vector":"0"}},{"base_weights":[2.5383531E-4],"categories":[],"categories_nodes":[],"categories_segments":[],"categories_sizes":[],"default_left":[0],"id":31,"left_children":[-1],"loss_changes":[0E0],"parents":[2147483647],"right_children":[-1],"split_conditions":[7.6150594E-5],"split_indices":[0],"split_type":[0],"sum_hessian":[3.19E2],"tree_param":{"num_deleted":"0","num_feature":"4","num_nodes":"1","size_leaf_vector":"0"}},{"base_weights":[1.7777979E-4],"categories":[],"categories_nodes":[],"categories_segments":[],"categories_sizes":[],"default_left":[0],"id":32,"left_children":[-1],"loss_changes":[0E0],"parents":[2147483647],"right_children":[-1],"split_conditions":[5.3333937E-5],"split_indices":[0],"split_type":[0],"sum_hessian":[3.19E2],"tree_param":{"num_deleted":"0","num_feature":"4","num_nodes":"1","size_leaf_vector":"0"}},{"base_weights":[1.2454092E-4],"categories":[],"categories_nodes":[],"categories_segments":[],"categories_sizes":[],"default_left":[0],"id":33,"left_children":[-1],"loss_changes":[0E0],"parents":[2147483647],"right_children":[-1],"split_conditions":[3.736228E-5],"split_indices":[0],"split_type":[0],"sum_hessian":[3.19E2],"tree_param":{"num_deleted":"0","num_feature":"4","num_nodes":"1","size_leaf_vector":"0"}},{"base_weights":[8.746386E-5],"categories":[],"categories_nodes":[],"categories_segments":[],"categories_sizes":[],"default_left":[0],"id":34,"left_children":[-1],"loss_changes":[0E0],"parents":[2147483647],"right_children":[-1],"split_conditions":[2.6239159E-5],"split_indices":[0],"split_type":[0],"sum_hessian":[3.19E2],"tree_param":{"num_deleted":"0","num_feature":"4","num_nodes":"1","size_leaf_vector":"0"}},{"base_weights":[6.084442E-5],"categories":[],"categories_nodes":[],"categories_segments":[],"categories_sizes":[],"default_left":[0],"id":35,"left_children":[-1],"loss_changes":[0E0],"parents":[2147483647],"right_children":[-1],"split_conditions":[1.8253328E-5],"split_indices":[0],"split_type":[0],"sum_hessian":[3.19E2],"tree_param":{"num_deleted":"0","num_feature":"4","num_nodes":"1","size_leaf_vector":"0"}},{"base_weights":[4.2781234E-5],"categories":[],"categories_nodes":[],"categories_segments":[],"categories_sizes":[],"default_left":[0],"id":36,"left_children":[-1],"loss_changes":[0E0],"parents":[2147483647],"right_children":[-1],"split_conditions":[1.2834371E-5],"split_indices":[0],"split_type":[0],"sum_hessian":[3.19E2],"tree_param":{"num_deleted":"0","num_feature":"4","num_nodes":"1","size_leaf_vector":"0"}},{"base_weights":[3.042221E-5],"categories":[],"categories_nodes":[],"categories_segments":[],"categories_sizes":[],"default_left":[0],"id":37,"left_children":[-1],"loss_changes":[0E0],"parents":[2147483647],"right_children":[-1],"split_conditions":[9.126664E-6],"split_indices":[0],"split_type":[0],"sum_hessian":[3.19E2],"tree_param":{"num_deleted":"0","num_feature":"4","num_nodes":"1","size_leaf_vector":"0"}},{"base_weights":[2.091527E-5],"categories":[],"categories_nodes":[],"categories_segments":[],"categories_sizes":[],"default_left":[0],"id":38,"left_children":[-1],"loss_changes":[0E0],"parents":[2147483647],"right_children":[-1],"split_conditions":[6.274581E-6],"split_indices":[0],"split_type":[0],"sum_hessian":[3.19E2],"tree_param":{"num_deleted":"0","num_feature":"4","num_nodes":"1","size_leaf_vector":"0"}},{"base_weights":[1.4260411E-5],"categories":[],"categories_nodes":[],"categories_segments":[],"categories_sizes":[],"default_left":[0],"id":39,"left_children":[-1],"loss_changes":[0E0],"parents":[2147483647],"right_children":[-1],"split_conditions":[4.2781235E-6],"split_indices":[0],"split_type":[0],"sum_hessian":[3.19E2],"tree_param":{"num_deleted":"0","num_feature":"4","num_nodes":"1","size_leaf_vector":"0"}},{"base_weights":[1.0457635E-5],"categories":[],"categories_nodes":[],"categories_segments":[],"categories_sizes":[],"default_left":[0],"id":40,"left_children":[-1],"loss_changes":[0E0],"parents":[2147483647],"right_children":[-1],"split_conditions":[3.1372906E-6],"split_indices":[0],"split_type":[0],"sum_hessian":[3.19E2],"tree_param":{"num_deleted":"0","num_feature":"4","num_nodes":"1","size_leaf_vector":"0"}},{"base_weights":[7.6055526E-6],"categories":[],"categories_nodes":[],"categories_segments":[],"categories_sizes":[],"default_left":[0],"id":41,"left_children":[-1],"loss_changes":[0E0],"parents":[2147483647],"right_children":[-1],"split_conditions":[2.281666E-6],"split_indices":[0],"split_type":[0],"sum_hessian":[3.19E2],"tree_param":{"num_deleted":"0","num_feature":"4","num_nodes":"1","size_leaf_vector":"0"}},{"base_weights":[5.7041643E-6],"categories":[],"categories_nodes":[],"categories_segments":[],"categories_sizes":[],"default_left":[0],"id":42,"left_children":[-1],"loss_changes":[0E0],"parents":[2147483647],"right_children":[-1],"split_conditions":[1.7112494E-6],"split_indices":[0],"split_type":[0],"sum_hessian":[3.19E2],"tree_param":{"num_deleted":"0","num_feature":"4","num_nodes":"1","size_leaf_vector":"0"}},{"base_weights":[3.8027763E-6],"categories":[],"categories_nodes":[],"categories_segments":[],"categories_sizes":[],"default_left":[0],"id":43,"left_children":[-1],"loss_changes":[0E0],"parents":[2147483647],"right_children":[-1],"split_conditions":[1.140833E-6],"split_indices":[0],"split_type":[0],"sum_hessian":[3.19E2],"tree_param":{"num_deleted":"0","num_feature":"4","num_nodes":"1","size_leaf_vector":"0"}},{"base_weights":[2.8520822E-6],"categories":[],"categories_nodes":[],"categories_segments":[],"categories_sizes":[],"default_left":[0],"id":44,"left_children":[-1],"loss_changes":[0E0],"parents":[2147483647],"right_children":[-1],"split_conditions":[8.556247E-7],"split_indices":[0],"split_type":[0],"sum_hessian":[3.19E2],"tree_param":{"num_deleted":"0","num_feature":"4","num_nodes":"1","size_leaf_vector":"0"}},{"base_weights":[1.9013881E-6],"categories":[],"categories_nodes":[],"categories_segments":[],"categories_sizes":[],"default_left":[0],"id":45,"left_children":[-1],"loss_changes":[0E0],"parents":[2147483647],"right_children":[-1],"split_conditions":[5.704165E-7],"split_indices":[0],"split_type":[0],"sum_hessian":[3.19E2],"tree_param":{"num_deleted":"0","num_feature":"4","num_nodes":"1","size_leaf_vector":"0"}},{"base_weights":[9.506941E-7],"categories":[],"categories_nodes":[],"categories_segments":[],"categories_sizes":[],"default_left":[0],"id":46,"left_children":[-1],"loss_changes":[0E0],"parents":[2147483647],"right_children":[-1],"split_conditions":[2.8520824E-7],"split_indices":[0],"split_type":[0],"sum_hessian":[3.19E2],"tree_param":{"num_deleted":"0","num_feature":"4","num_nodes":"1","size_leaf_vector":"0"}},{"base_weights":[9.506941E-7],"categories":[],"categories_nodes":[],"categories_segments":[],"categories_sizes":[],"default_left":[0],"id":47,"left_children":[-1],"loss_changes":[0E0],"parents":[2147483647],"right_children":[-1],"split_conditions":[2.8520824E-7],"split_indices":[0],"split_type":[0],"sum_hessian":[3.19E2],"tree_param":{"num_deleted":"0","num_feature":"4","num_nodes":"1","size_leaf_vector":"0"}},{"base_weights":[9.506941E-7],"categories":[],"categories_nodes":[],"categories_segments":[],"categories_sizes":[],"default_left":[0],"id":48,"left_children":[-1],"loss_changes":[0E0],"parents":[2147483647],"right_children":[-1],"split_conditions":[2.8520824E-7],"split_indices":[0],"split_type":[0],"sum_hessian":[3.19E2],"tree_param":{"num_deleted":"0","num_feature":"4","num_nodes":"1","size_leaf_vector":"0"}},{"base_weights":[9.506941E-7],"categories":[],"categories_nodes":[],"categories_segments":[],"categories_sizes":[],"default_left":[0],"id":49,"left_children":[-1],"loss_changes":[0E0],"parents":[2147483647],"right_children":[-1],"split_conditions":[2.8520824E-7],"split_indices":[0],"split_type":[0],"sum_hessian":[3.19E2],"tree_param":{"num_deleted":"0","num_feature":"4","num_nodes":"1","size_leaf_vector":"0"}},{"base_weights":[9.506941E-7],"categories":[],"categories_nodes":[],"categories_segments":[],"categories_sizes":[],"default_left":[0],"id":50,"left_children":[-1],"loss_changes":[0E0],"parents":[2147483647],"right_children":[-1],"split_conditions":[2.8520824E-7],"split_indices":[0],"split_type":[0],"sum_hessian":[3.19E2],"tree_param":{"num_deleted":"0","num_feature":"4","num_nodes":"1","size_leaf_vector":"0"}},{"base_weights":[9.506941E-7],"categories":[],"categories_nodes":[],"categories_segments":[],"categories_sizes":[],"default_left":[0],"id":51,"left_children":[-1],"loss_changes":[0E0],"parents":[2147483647],"right_children":[-1],"split_conditions":[2.8520824E-7],"split_indices":[0],"split_type":[0],"sum_hessian":[3.19E2],"tree_param":{"num_deleted":"0","num_feature":"4","num_nodes":"1","size_leaf_vector":"0"}},{"base_weights":[9.506941E-7],"categories":[],"categories_nodes":[],"categories_segments":[],"categories_sizes":[],"default_left":[0],"id":52,"left_children":[-1],"loss_changes":[0E0],"parents":[2147483647],"right_children":[-1],"split_conditions":[2.8520824E-7],"split_indices":[0],"split_type":[0],"sum_hessian":[3.19E2],"tree_param":{"num_deleted":"0","num_feature":"4","num_nodes":"1","size_leaf_vector":"0"}},{"base_weights":[9.506941E-7],"categories":[],"categories_nodes":[],"categories_segments":[],"categories_sizes":[],"default_left":[0],"id":53,"left_children":[-1],"loss_changes":[0E0],"parents":[2147483647],"right_children":[-1],"split_conditions":[2.8520824E-7],"split_indices":[0],"split_type":[0],"sum_hessian":[3.19E2],"tree_param":{"num_deleted":"0","num_feature":"4","num_nodes":"1","size_leaf_vector":"0"}},{"base_weights":[9.506941E-7],"categories":[],"categories_nodes":[],"categories_segments":[],"categories_sizes":[],"default_left":[0],"id":54,"left_children":[-1],"loss_changes":[0E0],"parents":[2147483647],"right_children":[-1],"split_conditions":[2.8520824E-7],"split_indices":[0],"split_type":[0],"sum_hessian":[3.19E2],"tree_param":{"num_deleted":"0","num_feature":"4","num_nodes":"1","size_leaf_vector":"0"}},{"base_weights":[9.506941E-7],"categories":[],"categories_nodes":[],"categories_segments":[],"categories_sizes":[],"default_left":[0],"id":55,"left_children":[-1],"loss_changes":[0E0],"parents":[2147483647],"right_children":[-1],"split_conditions":[2.8520824E-7],"split_indices":[0],"split_type":[0],"sum_hessian":[3.19E2],"tree_param":{"num_deleted":"0","num_feature":"4","num_nodes":"1","size_leaf_vector":"0"}},{"base_weights":[9.506941E-7],"categories":[],"categories_nodes":[],"categories_segments":[],"categories_sizes":[],"default_left":[0],"id":56,"left_children":[-1],"loss_changes":[0E0],"parents":[2147483647],"right_children":[-1],"split_conditions":[2.8520824E-7],"split_indices":[0],"split_type":[0],"sum_hessian":[3.19E2],"tree_param":{"num_deleted":"0","num_feature":"4","num_nodes":"1","size_leaf_vector":"0"}},{"base_weights":[9.506941E-7],"categories":[],"categories_nodes":[],"categories_segments":[],"categories_sizes":[],"default_left":[0],"id":57,"left_children":[-1],"loss_changes":[0E0],"parents":[2147483647],"right_children":[-1],"split_conditions":[2.8520824E-7],"split_indices":[0],"split_type":[0],"sum_hessian":[3.19E2],"tree_param":{"num_deleted":"0","num_feature":"4","num_nodes":"1","size_leaf_vector":"0"}},{"base_weights":[9.506941E-7],"categories":[],"categories_nodes":[],"categories_segments":[],"categories_sizes":[],"default_left":[0],"id":58,"left_children":[-1],"loss_changes":[0E0],"parents":[2147483647],"right_children":[-1],"split_conditions":[2.8520824E-7],"split_indices":[0],"split_type":[0],"sum_hessian":[3.19E2],"tree_param":{"num_deleted":"0","num_feature":"4","num_nodes":"1","size_leaf_vector":"0"}},{"base_weights":[9.506941E-7],"categories":[],"categories_nodes":[],"categories_segments":[],"categories_sizes":[],"default_left":[0],"id":59,"left_children":[-1],"loss_changes":[0E0],"parents":[2147483647],"right_children":[-1],"split_conditions":[2.8520824E-7],"split_indices":[0],"split_type":[0],"sum_hessian":[3.19E2],"tree_param":{"num_deleted":"0","num_feature":"4","num_nodes":"1","size_leaf_vector":"0"}},{"base_weights":[9.506941E-7],"categories":[],"categories_nodes":[],"categories_segments":[],"categories_sizes":[],"default_left":[0],"id":60,"left_children":[-1],"loss_changes":[0E0],"parents":[2147483647],"right_children":[-1],"split_conditions":[2.8520824E-7],"split_indices":[0],"split_type":[0],"sum_hessian":[3.19E2],"tree_param":{"num_deleted":"0","num_feature":"4","num_nodes":"1","size_leaf_vector":"0"}},{"base_weights":[9.506941E-7],"categories":[],"categories_nodes":[],"categories_segments":[],"categories_sizes":[],"default_left":[0],"id":61,"left_children":[-1],"loss_changes":[0E0],"parents":[2147483647],"right_children":[-1],"split_conditions":[2.8520824E-7],"split_indices":[0],"split_type":[0],"sum_hessian":[3.19E2],"tree_param":{"num_deleted":"0","num_feature":"4","num_nodes":"1","size_leaf_vector":"0"}},{"base_weights":[9.506941E-7],"categories":[],"categories_nodes":[],"categories_segments":[],"categories_sizes":[],"default_left":[0],"id":62,"left_children":[-1],"loss_changes":[0E0],"parents":[2147483647],"right_children":[-1],"split_conditions":[2.8520824E-7],"split_indices":[0],"split_type":[0],"sum_hessian":[3.19E2],"tree_param":{"num_deleted":"0","num_feature":"4","num_nodes":"1","size_leaf_vector":"0"}},{"base_weights":[9.506941E-7],"categories":[],"categories_nodes":[],"categories_segments":[],"categories_sizes":[],"default_left":[0],"id":63,"left_children":[-1],"loss_changes":[0E0],"parents":[2147483647],"right_children":[-1],"split_conditions":[2.8520824E-7],"split_indices":[0],"split_type":[0],"sum_hessian":[3.19E2],"tree_param":{"num_deleted":"0","num_feature":"4","num_nodes":"1","size_leaf_vector":"0"}},{"base_weights":[9.506941E-7],"categories":[],"categories_nodes":[],"categories_segments":[],"categories_sizes":[],"default_left":[0],"id":64,"left_children":[-1],"loss_changes":[0E0],"parents":[2147483647],"right_children":[-1],"split_conditions":[2.8520824E-7],"split_indices":[0],"split_type":[0],"sum_hessian":[3.19E2],"tree_param":{"num_deleted":"0","num_feature":"4","num_nodes":"1","size_leaf_vector":"0"}},{"base_weights":[9.506941E-7],"categories":[],"categories_nodes":[],"categories_segments":[],"categories_sizes":[],"default_left":[0],"id":65,"left_children":[-1],"loss_changes":[0E0],"parents":[2147483647],"right_children":[-1],"split_conditions":[2.8520824E-7],"split_indices":[0],"split_type":[0],"sum_hessian":[3.19E2],"tree_param":{"num_deleted":"0","num_feature":"4","num_nodes":"1","size_leaf_vector":"0"}},{"base_weights":[9.506941E-7],"categories":[],"categories_nodes":[],"categories_segments":[],"categories_sizes":[],"default_left":[0],"id":66,"left_children":[-1],"loss_changes":[0E0],"parents":[2147483647],"right_children":[-1],"split_conditions":[2.8520824E-7],"split_indices":[0],"split_type":[0],"sum_hessian":[3.19E2],"tree_param":{"num_deleted":"0","num_feature":"4","num_nodes":"1","size_leaf_vector":"0"}},{"base_weights":[9.506941E-7],"categories":[],"categories_nodes":[],"categories_segments":[],"categories_sizes":[],"default_left":[0],"id":67,"left_children":[-1],"loss_changes":[0E0],"parents":[2147483647],"right_children":[-1],"split_conditions":[2.8520824E-7],"split_indices":[0],"split_type":[0],"sum_hessian":[3.19E2],"tree_param":{"num_deleted":"0","num_feature":"4","num_nodes":"1","size_leaf_vector":"0"}},{"base_weights":[9.506941E-7],"categories":[],"categories_nodes":[],"categories_segments":[],"categories_sizes":[],"default_left":[0],"id":68,"left_children":[-1],"loss_changes":[0E0],"parents":[2147483647],"right_children":[-1],"split_conditions":[2.8520824E-7],"split_indices":[0],"split_type":[0],"sum_hessian":[3.19E2],"tree_param":{"num_deleted":"0","num_feature":"4","num_nodes":"1","size_leaf_vector":"0"}},{"base_weights":[9.506941E-7],"categories":[],"categories_nodes":[],"categories_segments":[],"categories_sizes":[],"default_left":[0],"id":69,"left_children":[-1],"loss_changes":[0E0],"parents":[2147483647],"right_children":[-1],"split_conditions":[2.8520824E-7],"split_indices":[0],"split_type":[0],"sum_hessian":[3.19E2],"tree_param":{"num_deleted":"0","num_feature":"4","num_nodes":"1","size_leaf_vector":"0"}},{"base_weights":[9.506941E-7],"categories":[],"categories_nodes":[],"categories_segments":[],"categories_sizes":[],"default_left":[0],"id":70,"left_children":[-1],"loss_changes":[0E0],"parents":[2147483647],"right_children":[-1],"split_conditions":[2.8520824E-7],"split_indices":[0],"split_type":[0],"sum_hessian":[3.19E2],"tree_param":{"num_deleted":"0","num_feature":"4","num_nodes":"1","size_leaf_vector":"0"}},{"base_weights":[9.506941E-7],"categories":[],"categories_nodes":[],"categories_segments":[],"categories_sizes":[],"default_left":[0],"id":71,"left_children":[-1],"loss_changes":[0E0],"parents":[2147483647],"right_children":[-1],"split_conditions":[2.8520824E-7],"split_indices":[0],"split_type":[0],"sum_hessian":[3.19E2],"tree_param":{"num_deleted":"0","num_feature":"4","num_nodes":"1","size_leaf_vector":"0"}},{"base_weights":[9.506941E-7],"categories":[],"categories_nodes":[],"categories_segments":[],"categories_sizes":[],"default_left":[0],"id":72,"left_children":[-1],"loss_changes":[0E0],"parents":[2147483647],"right_children":[-1],"split_conditions":[2.8520824E-7],"split_indices":[0],"split_type":[0],"sum_hessian":[3.19E2],"tree_param":{"num_deleted":"0","num_feature":"4","num_nodes":"1","size_leaf_vector":"0"}},{"base_weights":[9.506941E-7],"categories":[],"categories_nodes":[],"categories_segments":[],"categories_sizes":[],"default_left":[0],"id":73,"left_children":[-1],"loss_changes":[0E0],"parents":[2147483647],"right_children":[-1],"split_conditions":[2.8520824E-7],"split_indices":[0],"split_type":[0],"sum_hessian":[3.19E2],"tree_param":{"num_deleted":"0","num_feature":"4","num_nodes":"1","size_leaf_vector":"0"}},{"base_weights":[9.506941E-7],"categories":[],"categories_nodes":[],"categories_segments":[],"categories_sizes":[],"default_left":[0],"id":74,"left_children":[-1],"loss_changes":[0E0],"parents":[2147483647],"right_children":[-1],"split_conditions":[2.8520824E-7],"split_indices":[0],"split_type":[0],"sum_hessian":[3.19E2],"tree_param":{"num_deleted":"0","num_feature":"4","num_nodes":"1","size_leaf_vector":"0"}},{"base_weights":[9.506941E-7],"categories":[],"categories_nodes":[],"categories_segments":[],"categories_sizes":[],"default_left":[0],"id":75,"left_children":[-1],"loss_changes":[0E0],"parents":[2147483647],"right_children":[-1],"split_conditions":[2.8520824E-7],"split_indices":[0],"split_type":[0],"sum_hessian":[3.19E2],"tree_param":{"num_deleted":"0","num_feature":"4","num_nodes":"1","size_leaf_vector":"0"}},{"base_weights":[9.506941E-7],"categories":[],"categories_nodes":[],"categories_segments":[],"categories_sizes":[],"default_left":[0],"id":76,"left_children":[-1],"loss_changes":[0E0],"parents":[2147483647],"right_children":[-1],"split_conditions":[2.8520824E-7],"split_indices":[0],"split_type":[0],"sum_hessian":[3.19E2],"tree_param":{"num_deleted":"0","num_feature":"4","num_nodes":"1","size_leaf_vector":"0"}},{"base_weights":[9.506941E-7],"categories":[],"categories_nodes":[],"categories_segments":[],"categories_sizes":[],"default_left":[0],"id":77,"left_children":[-1],"loss_changes":[0E0],"parents":[2147483647],"right_children":[-1],"split_conditions":[2.8520824E-7],"split_indices":[0],"split_type":[0],"sum_hessian":[3.19E2],"tree_param":{"num_deleted":"0","num_feature":"4","num_nodes":"1","size_leaf_vector":"0"}},{"base_weights":[9.506941E-7],"categories":[],"categories_nodes":[],"categories_segments":[],"categories_sizes":[],"default_left":[0],"id":78,"left_children":[-1],"loss_changes":[0E0],"parents":[2147483647],"right_children":[-1],"split_conditions":[2.8520824E-7],"split_indices":[0],"split_type":[0],"sum_hessian":[3.19E2],"tree_param":{"num_deleted":"0","num_feature":"4","num_nodes":"1","size_leaf_vector":"0"}},{"base_weights":[9.506941E-7],"categories":[],"categories_nodes":[],"categories_segments":[],"categories_sizes":[],"default_left":[0],"id":79,"left_children":[-1],"loss_changes":[0E0],"parents":[2147483647],"right_children":[-1],"split_conditions":[2.8520824E-7],"split_indices":[0],"split_type":[0],"sum_hessian":[3.19E2],"tree_param":{"num_deleted":"0","num_feature":"4","num_nodes":"1","size_leaf_vector":"0"}},{"base_weights":[9.506941E-7],"categories":[],"categories_nodes":[],"categories_segments":[],"categories_sizes":[],"default_left":[0],"id":80,"left_children":[-1],"loss_changes":[0E0],"parents":[2147483647],"right_children":[-1],"split_conditions":[2.8520824E-7],"split_indices":[0],"split_type":[0],"sum_hessian":[3.19E2],"tree_param":{"num_deleted":"0","num_feature":"4","num_nodes":"1","size_leaf_vector":"0"}},{"base_weights":[9.506941E-7],"categories":[],"categories_nodes":[],"categories_segments":[],"categories_sizes":[],"default_left":[0],"id":81,"left_children":[-1],"loss_changes":[0E0],"parents":[2147483647],"right_children":[-1],"split_conditions":[2.8520824E-7],"split_indices":[0],"split_type":[0],"sum_hessian":[3.19E2],"tree_param":{"num_deleted":"0","num_feature":"4","num_nodes":"1","size_leaf_vector":"0"}},{"base_weights":[9.506941E-7],"categories":[],"categories_nodes":[],"categories_segments":[],"categories_sizes":[],"default_left":[0],"id":82,"left_children":[-1],"loss_changes":[0E0],"parents":[2147483647],"right_children":[-1],"split_conditions":[2.8520824E-7],"split_indices":[0],"split_type":[0],"sum_hessian":[3.19E2],"tree_param":{"num_deleted":"0","num_feature":"4","num_nodes":"1","size_leaf_vector":"0"}},{"base_weights":[9.506941E-7],"categories":[],"categories_nodes":[],"categories_segments":[],"categories_sizes":[],"default_left":[0],"id":83,"left_children":[-1],"loss_changes":[0E0],"parents":[2147483647],"right_children":[-1],"split_conditions":[2.8520824E-7],"split_indices":[0],"split_type":[0],"sum_hessian":[3.19E2],"tree_param":{"num_deleted":"0","num_feature":"4","num_nodes":"1","size_leaf_vector":"0"}},{"base_weights":[9.506941E-7],"categories":[],"categories_nodes":[],"categories_segments":[],"categories_sizes":[],"default_left":[0],"id":84,"left_children":[-1],"loss_changes":[0E0],"parents":[2147483647],"right_children":[-1],"split_conditions":[2.8520824E-7],"split_indices":[0],"split_type":[0],"sum_hessian":[3.19E2],"tree_param":{"num_deleted":"0","num_feature":"4","num_nodes":"1","size_leaf_vector":"0"}},{"base_weights":[9.506941E-7],"categories":[],"categories_nodes":[],"categories_segments":[],"categories_sizes":[],"default_left":[0],"id":85,"left_children":[-1],"loss_changes":[0E0],"parents":[2147483647],"right_children":[-1],"split_conditions":[2.8520824E-7],"split_indices":[0],"split_type":[0],"sum_hessian":[3.19E2],"tree_param":{"num_deleted":"0","num_feature":"4","num_nodes":"1","size_leaf_vector":"0"}},{"base_weights":[9.506941E-7],"categories":[],"categories_nodes":[],"categories_segments":[],"categories_sizes":[],"default_left":[0],"id":86,"left_children":[-1],"loss_changes":[0E0],"parents":[2147483647],"right_children":[-1],"split_conditions":[2.8520824E-7],"split_indices":[0],"split_type":[0],"sum_hessian":[3.19E2],"tree_param":{"num_deleted":"0","num_feature":"4","num_nodes":"1","size_leaf_vector":"0"}},{"base_weights":[9.506941E-7],"categories":[],"categories_nodes":[],"categories_segments":[],"categories_sizes":[],"default_left":[0],"id":87,"left_children":[-1],"loss_changes":[0E0],"parents":[2147483647],"right_children":[-1],"split_conditions":[2.8520824E-7],"split_indices":[0],"split_type":[0],"sum_hessian":[3.19E2],"tree_param":{"num_deleted":"0","num_feature":"4","num_nodes":"1","size_leaf_vector":"0"}},{"base_weights":[9.506941E-7],"categories":[],"categories_nodes":[],"categories_segments":[],"categories_sizes":[],"default_left":[0],"id":88,"left_children":[-1],"loss_changes":[0E0],"parents":[2147483647],"right_children":[-1],"split_conditions":[2.8520824E-7],"split_indices":[0],"split_type":[0],"sum_hessian":[3.19E2],"tree_param":{"num_deleted":"0","num_feature":"4","num_nodes":"1","size_leaf_vector":"0"}},{"base_weights":[9.506941E-7],"categories":[],"categories_nodes":[],"categories_segments":[],"categories_sizes":[],"default_left":[0],"id":89,"left_children":[-1],"loss_changes":[0E0],"parents":[2147483647],"right_children":[-1],"split_conditions":[2.8520824E-7],"split_indices":[0],"split_type":[0],"sum_hessian":[3.19E2],"tree_param":{"num_deleted":"0","num_feature":"4","num_nodes":"1","size_leaf_vector":"0"}},{"base_weights":[9.506941E-7],"categories":[],"categories_nodes":[],"categories_segments":[],"categories_sizes":[],"default_left":[0],"id":90,"left_children":[-1],"loss_changes":[0E0],"parents":[2147483647],"right_children":[-1],"split_conditions":[2.8520824E-7],"split_indices":[0],"split_type":[0],"sum_hessian":[3.19E2],"tree_param":{"num_deleted":"0","num_feature":"4","num_nodes":"1","size_leaf_vector":"0"}},{"base_weights":[9.506941E-7],"categories":[],"categories_nodes":[],"categories_segments":[],"categories_sizes":[],"default_left":[0],"id":91,"left_children":[-1],"loss_changes":[0E0],"parents":[2147483647],"right_children":[-1],"split_conditions":[2.8520824E-7],"split_indices":[0],"split_type":[0],"sum_hessian":[3.19E2],"tree_param":{"num_deleted":"0","num_feature":"4","num_nodes":"1","size_leaf_vector":"0"}},{"base_weights":[9.506941E-7],"categories":[],"categories_nodes":[],"categories_segments":[],"categories_sizes":[],"default_left":[0],"id":92,"left_children":[-1],"loss_changes":[0E0],"parents":[2147483647],"right_children":[-1],"split_conditions":[2.8520824E-7],"split_indices":[0],"split_type":[0],"sum_hessian":[3.19E2],"tree_param":{"num_deleted":"0","num_feature":"4","num_nodes":"1","size_leaf_vector":"0"}},{"base_weights":[9.506941E-7],"categories":[],"categories_nodes":[],"categories_segments":[],"categories_sizes":[],"default_left":[0],"id":93,"left_children":[-1],"loss_changes":[0E0],"parents":[2147483647],"right_children":[-1],"split_conditions":[2.8520824E-7],"split_indices":[0],"split_type":[0],"sum_hessian":[3.19E2],"tree_param":{"num_deleted":"0","num_feature":"4","num_nodes":"1","size_leaf_vector":"0"}},{"base_weights":[9.506941E-7],"categories":[],"categories_nodes":[],"categories_segments":[],"categories_sizes":[],"default_left":[0],"id":94,"left_children":[-1],"loss_changes":[0E0],"parents":[2147483647],"right_children":[-1],"split_conditions":[2.8520824E-7],"split_indices":[0],"split_type":[0],"sum_hessian":[3.19E2],"tree_param":{"num_deleted":"0","num_feature":"4","num_nodes":"1","size_leaf_vector":"0"}},{"base_weights":[9.506941E-7],"categories":[],"categories_nodes":[],"categories_segments":[],"categories_sizes":[],"default_left":[0],"id":95,"left_children":[-1],"loss_changes":[0E0],"parents":[2147483647],"right_children":[-1],"split_conditions":[2.8520824E-7],"split_indices":[0],"split_type":[0],"sum_hessian":[3.19E2],"tree_param":{"num_deleted":"0","num_feature":"4","num_nodes":"1","size_leaf_vector":"0"}},{"base_weights":[9.506941E-7],"categories":[],"categories_nodes":[],"categories_segments":[],"categories_sizes":[],"default_left":[0],"id":96,"left_children":[-1],"loss_changes":[0E0],"parents":[2147483647],"right_children":[-1],"split_conditions":[2.8520824E-7],"split_indices":[0],"split_type":[0],"sum_hessian":[3.19E2],"tree_param":{"num_deleted":"0","num_feature":"4","num_nodes":"1","size_leaf_vector":"0"}},{"base_weights":[9.506941E-7],"categories":[],"categories_nodes":[],"categories_segments":[],"categories_sizes":[],"default_left":[0],"id":97,"left_children":[-1],"loss_changes":[0E0],"parents":[2147483647],"right_children":[-1],"split_conditions":[2.8520824E-7],"split_indices":[0],"split_type":[0],"sum_hessian":[3.19E2],"tree_param":{"num_deleted":"0","num_feature":"4","num_nodes":"1","size_leaf_vector":"0"}},{"base_weights":[9.506941E-7],"categories":[],"categories_nodes":[],"categories_segments":[],"categories_sizes":[],"default_left":[0],"id":98,"left_children":[-1],"loss_changes":[0E0],"parents":[2147483647],"right_children":[-1],"split_conditions":[2.8520824E-7],"split_indices":[0],"split_type":[0],"sum_hessian":[3.19E2],"tree_param":{"num_deleted":"0","num_feature":"4","num_nodes":"1","size_leaf_vector":"0"}},{"base_weights":[9.506941E-7],"categories":[],"categories_nodes":[],"categories_segments":[],"categories_sizes":[],"default_left":[0],"id":99,"left_children":[-1],"loss_changes":[0E0],"parents":[2147483647],"right_children":[-1],"split_conditions":[2.8520824E-7],"split_indices":[0],"split_type":[0],"sum_hessian":[3.19E2],"tree_param":{"num_deleted":"0","num_feature":"4","num_nodes":"1","size_leaf_vector":"0"}}]},"name":"gbtree"},"learner_model_param":{"base_score":"5E-1","boost_from_average":"1","num_class":"0","num_feature":"4","num_target":"1"},"objective":{"name":"reg:squarederror","reg_loss_param":{"scale_pos_weight":"1"}}},"version":[1,7,2]}